kudaf_extension/__init__.py
kudaf_extension/app.py
kudaf_extension/auth.py
kudaf_extension/handler.py
kudaf_extension/notebook.py
kudaf_extension/start_up.py
kudaf_extension/utils.py
kudaf_jupyter_server_extension-0.3.0.dist-info/LICENSE.md
kudaf_jupyter_server_extension-0.3.0.dist-info/METADATA
kudaf_jupyter_server_extension-0.3.0.dist-info/WHEEL
kudaf_jupyter_server_extension-0.3.0.dist-info/RECORD
