Metadata-Version: 2.3
Name: kudaf_jupyter_server_extension
Version: 0.3.0
Summary: Kudaf Data Consumer Jupyter server extension for JupyterLab. It provides the basic infrastructure to interact with the Kudaf system
License: MIT
Author: Daniel Díguele,  Sikt - Kunnskapssektorens tjenesteleverandør 
Author-email: daniel.diguele@sikt.no
Maintainer: Daniel Díguele,  Sikt - Kunnskapssektorens tjenesteleverandør 
Maintainer-email: daniel.diguele@sikt.no
Requires-Python: >=3.9.16,<4.0.0
Classifier: Framework :: Jupyter :: JupyterLab
Classifier: License :: OSI Approved :: MIT License
Classifier: Operating System :: OS Independent
Classifier: Programming Language :: Python :: 3
Classifier: Programming Language :: Python :: 3.10
Classifier: Programming Language :: Python :: 3.11
Classifier: Programming Language :: Python :: 3.12
Classifier: Programming Language :: Python :: 3.13
Requires-Dist: authlib (>=1.3.0,<2.0.0)
Requires-Dist: httpx (>=0.27.0,<0.28.0)
Requires-Dist: ipylab (>=1.0.0,<2.0.0)
Requires-Dist: jupyter_server (>=2.7.0,<3.0.0)
Requires-Dist: jupyterlab (==3.6.5)
Requires-Dist: pyjwt (>=2.8.0,<3.0.0)
Project-URL: Bug Tracker, https://gitlab.sikt.no/kudaf/jupyterlab/-/issues
Project-URL: Homepage, https://gitlab.sikt.no/kudaf/jupyterlab
